chevette/__init__.py
chevette/chevette.py
chevette/cli.py
chevette/exceptions/__init__.py
chevette/exceptions/no_config.py
chevette/markdown/__init__.py
chevette/markdown/article.py
chevette/markdown/page.py
chevette/markdown/parser.py
chevette/server/__init__.py
chevette/server/server.py
chevette/tests/__init__.py
chevette/tests/conftest.py
chevette/tests/test_helpers.py
chevette/utils/__init__.py
chevette/utils/constants.py
chevette/utils/helpers.py
chevette-0.1.0.dist-info/METADATA
chevette-0.1.0.dist-info/WHEEL
chevette-0.1.0.dist-info/entry_points.txt
chevette-0.1.0.dist-info/top_level.txt
chevette-0.1.0.dist-info/RECORD
