Metadata-Version: 2.1
Name: chevette
Version: 0.1.0
Summary: Chevette is a MarkDown powered static blog engine.
Home-page: https://github.com/Zabanaa/chevette
Author: Karim C
Author-email: karim.cheurfi@gmail.com
License: UNKNOWN
Keywords: static site generator
Platform: UNKNOWN
Classifier: Development Status :: 3 - Alpha
Classifier: Programming Language :: Python :: 3.7
Classifier: Intended Audience :: Developers
Classifier: Intended Audience :: End Users/Desktop
Classifier: Operating System :: OS Independent
Classifier: Topic :: Internet :: WWW/HTTP :: Dynamic Content :: News/Diary
Requires-Python: >=3.7
Requires-Dist: jinja2
Requires-Dist: misaka
Requires-Dist: python-frontmatter
Requires-Dist: click
Requires-Dist: colorama
